pyearth/__init__.py
pyearth/_basis.pxd
pyearth/_basis.pyx
pyearth/_forward.pxd
pyearth/_forward.pyx
pyearth/_forward.pyxdep
pyearth/_knot_search.pxd
pyearth/_knot_search.pyx
pyearth/_knot_search.pyxdep
pyearth/_pruning.pxd
pyearth/_pruning.pyx
pyearth/_pruning.pyxdep
pyearth/_qr.pxd
pyearth/_qr.pyx
pyearth/_qr.pyxdep
pyearth/_record.pxd
pyearth/_record.pyx
pyearth/_record.pyxdep
pyearth/_types.pxd
pyearth/_types.pyx
pyearth/_util.pxd
pyearth/_util.pyx
pyearth/_util.pyxdep
pyearth/earth.py
pyearth/export.py
pyearth/_basis.cp312-win_amd64.pyd
pyearth/_forward.cp312-win_amd64.pyd
pyearth/_knot_search.cp312-win_amd64.pyd
pyearth/_pruning.cp312-win_amd64.pyd
pyearth/_qr.cp312-win_amd64.pyd
pyearth/_record.cp312-win_amd64.pyd
pyearth/_types.cp312-win_amd64.pyd
pyearth/_util.cp312-win_amd64.pyd
py_earth2-0.2.0.dist-info/METADATA
py_earth2-0.2.0.dist-info/WHEEL
py_earth2-0.2.0.dist-info/licenses/LICENSE.txt
py_earth2-0.2.0.dist-info/RECORD
