Metadata-Version: 2.4
Name: py-earth2
Version: 0.2.0
Summary: A Python implementation of Jerome Friedman's Multivariate Adaptive Regression Splines.
Author-email: Jason Rudy <jcrudy@gmail.com>
License: Copyright (c) 2025, Felix Williams
License-File: LICENSE.txt
Classifier: Development Status :: 3 - Alpha
Classifier: Intended Audience :: Developers
Classifier: Intended Audience :: Science/Research
Classifier: License :: OSI Approved :: BSD License
Classifier: Operating System :: MacOS
Classifier: Operating System :: Microsoft :: Windows
Classifier: Operating System :: POSIX
Classifier: Operating System :: Unix
Classifier: Programming Language :: Cython
Classifier: Programming Language :: Python
Classifier: Programming Language :: Python :: 3
Classifier: Programming Language :: Python :: 3.9
Classifier: Topic :: Scientific/Engineering
Classifier: Topic :: Software Development
Requires-Python: >=3.10
Requires-Dist: numpy>=1
Requires-Dist: scikit-learn>=0.16
Requires-Dist: scipy>=1
Provides-Extra: export
Requires-Dist: sympy; extra == 'export'
